{"name":"Crear una nueva unidad de negocio","id":"agendar-una-reunión-a-unidad-de-negocio-y-asociar-contacto-previamente-creados;crear-una-nueva-unidad-de-negocio","scenarioId":"casos:Crear una nueva unidad de negocio","methodName":"Crear una nueva unidad de negocio","testSteps":[{"number":1,"description":"Dado que el usuario acceda a la pagina Serenity.is","duration":12189,"startTime":"2024-08-05T16:04:22.221146400-05:00[America/Panama]","screenshots":[{"screenshot":"8ff90271b2f5f99b401e7afc6f4fff2c1fd681b04b6394d8a41fbb311dab4665.png","timeStamp":1722891874410,"screenshotName":"8ff90271b2f5f99b401e7afc6f4fff2c1fd681b04b6394d8a41fbb311dab4665.png"}],"result":"SUCCESS","precondition":false,"level":0,"children":[{"number":2,"description":"Actor ir pagina serenity","duration":11176,"startTime":"2024-08-05T16:04:23.227308700-05:00[America/Panama]","screenshots":[{"screenshot":"8ff90271b2f5f99b401e7afc6f4fff2c1fd681b04b6394d8a41fbb311dab4665.png","timeStamp":1722891874403,"screenshotName":"8ff90271b2f5f99b401e7afc6f4fff2c1fd681b04b6394d8a41fbb311dab4665.png"}],"result":"SUCCESS","precondition":false,"level":1,"children":[{"number":3,"description":"actor opens the Pagina inicio sesion","duration":11113,"startTime":"2024-08-05T16:04:23.274192300-05:00[America/Panama]","screenshots":[{"screenshot":"8ff90271b2f5f99b401e7afc6f4fff2c1fd681b04b6394d8a41fbb311dab4665.png","timeStamp":1722891874387,"screenshotName":"8ff90271b2f5f99b401e7afc6f4fff2c1fd681b04b6394d8a41fbb311dab4665.png"}],"result":"SUCCESS","precondition":false,"level":2}]}]},{"number":4,"description":"Y acceda con el rol admin\r\n| usuario | contraseña |\r\n| admin | serenity |","duration":12223,"startTime":"2024-08-05T16:04:34.410656300-05:00[America/Panama]","screenshots":[{"screenshot":"1a098020e9eb3cf5b03027b4c9b39a365c99da3f5bcc6ae90cf4f665c51ed77c.png","timeStamp":1722891886633,"screenshotName":"1a098020e9eb3cf5b03027b4c9b39a365c99da3f5bcc6ae90cf4f665c51ed77c.png"}],"result":"SUCCESS","precondition":false,"level":0,"children":[{"number":5,"description":"Actor inicio sesion","duration":12190,"startTime":"2024-08-05T16:04:34.419702400-05:00[America/Panama]","screenshots":[{"screenshot":"1a098020e9eb3cf5b03027b4c9b39a365c99da3f5bcc6ae90cf4f665c51ed77c.png","timeStamp":1722891886610,"screenshotName":"1a098020e9eb3cf5b03027b4c9b39a365c99da3f5bcc6ae90cf4f665c51ed77c.png"}],"result":"SUCCESS","precondition":false,"level":1,"children":[{"number":6,"description":"actor enters \u0027admin\u0027 into By.id: LoginPanel0_Username","duration":10291,"startTime":"2024-08-05T16:04:34.529668900-05:00[America/Panama]","screenshots":[{"screenshot":"e8b5f97980f6145e0374352cf93b535c58c66b6caf9a2dcc73d36eec9346ae1c.png","timeStamp":1722891884821,"screenshotName":"e8b5f97980f6145e0374352cf93b535c58c66b6caf9a2dcc73d36eec9346ae1c.png"}],"result":"SUCCESS","precondition":false,"level":2},{"number":7,"description":"actor enters \u0027serenity\u0027 into By.id: LoginPanel0_Password","duration":381,"startTime":"2024-08-05T16:04:44.821367800-05:00[America/Panama]","screenshots":[{"screenshot":"10f0c499c86a4ca3f3d4f2be69365c5f38aba6b5829831e9d43f07e9e3afaa3b.png","timeStamp":1722891885202,"screenshotName":"10f0c499c86a4ca3f3d4f2be69365c5f38aba6b5829831e9d43f07e9e3afaa3b.png"}],"result":"SUCCESS","precondition":false,"level":2},{"number":8,"description":"actor clicks on [By.id: LoginPanel0_LoginButton]","duration":1391,"startTime":"2024-08-05T16:04:45.202782-05:00[America/Panama]","screenshots":[{"screenshot":"1a098020e9eb3cf5b03027b4c9b39a365c99da3f5bcc6ae90cf4f665c51ed77c.png","timeStamp":1722891886594,"screenshotName":"1a098020e9eb3cf5b03027b4c9b39a365c99da3f5bcc6ae90cf4f665c51ed77c.png"}],"result":"SUCCESS","precondition":false,"level":2}]}]},{"number":9,"description":"Cuando el usuario despliegue el modulo Organización, acceda a la funcionalidad Unidades de negocio","duration":1621,"startTime":"2024-08-05T16:04:46.633667-05:00[America/Panama]","screenshots":[{"screenshot":"47e76345a71146d97253e4aadd1d4b40e59c3d35653da53dec6cf3fa94405e74.png","timeStamp":1722891888255,"screenshotName":"47e76345a71146d97253e4aadd1d4b40e59c3d35653da53dec6cf3fa94405e74.png"}],"result":"SUCCESS","precondition":false,"level":0,"children":[{"number":10,"description":"Actor ir pagina unidad de negocios","duration":1579,"startTime":"2024-08-05T16:04:46.656683900-05:00[America/Panama]","screenshots":[{"screenshot":"47e76345a71146d97253e4aadd1d4b40e59c3d35653da53dec6cf3fa94405e74.png","timeStamp":1722891888236,"screenshotName":"47e76345a71146d97253e4aadd1d4b40e59c3d35653da53dec6cf3fa94405e74.png"}],"result":"SUCCESS","precondition":false,"level":1,"children":[{"number":11,"description":"actor clicks on SECCION_ORGANIZACION","duration":466,"startTime":"2024-08-05T16:04:46.694219600-05:00[America/Panama]","screenshots":[{"screenshot":"5bbfa718853ec2b92037b7c168646eadcd4921bffc72a91cc78ed981b9e4f271.png","timeStamp":1722891887160,"screenshotName":"5bbfa718853ec2b92037b7c168646eadcd4921bffc72a91cc78ed981b9e4f271.png"}],"result":"SUCCESS","precondition":false,"level":2},{"number":12,"description":"actor clicks on FUNCIONALIDAD_UNIDAD_NEGOCIO","duration":1056,"startTime":"2024-08-05T16:04:47.162583700-05:00[America/Panama]","screenshots":[{"screenshot":"47e76345a71146d97253e4aadd1d4b40e59c3d35653da53dec6cf3fa94405e74.png","timeStamp":1722891888219,"screenshotName":"47e76345a71146d97253e4aadd1d4b40e59c3d35653da53dec6cf3fa94405e74.png"}],"result":"SUCCESS","precondition":false,"level":2}]}]},{"number":13,"description":"Y Selecciona la opción Nuevo Unidad de negocio e ingrese los datos requeridos\r\n| nombre_unidad | unidad_principal |\r\n| UdN_25 | Catherine |","duration":3264,"startTime":"2024-08-05T16:04:48.255064500-05:00[America/Panama]","screenshots":[{"screenshot":"bec6a6c453bd08296f48f0bee60287eb62f56fa5b4aa0e0fd24c9bc33ac2ae43.png","timeStamp":1722891891519,"screenshotName":"bec6a6c453bd08296f48f0bee60287eb62f56fa5b4aa0e0fd24c9bc33ac2ae43.png"}],"result":"SUCCESS","precondition":false,"level":0,"children":[{"number":14,"description":"Actor crear unidad negocio","duration":3009,"startTime":"2024-08-05T16:04:48.270157800-05:00[America/Panama]","screenshots":[{"screenshot":"c0e35456925482ecdac08eaca138965af214981bab42d6fd6aa5661fabde5688.png","timeStamp":1722891891279,"screenshotName":"c0e35456925482ecdac08eaca138965af214981bab42d6fd6aa5661fabde5688.png"}],"result":"SUCCESS","precondition":false,"level":1,"children":[{"number":15,"description":"actor clicks on BOTON_NUEVA_UNIDAD","duration":532,"startTime":"2024-08-05T16:04:48.304179100-05:00[America/Panama]","screenshots":[{"screenshot":"afddf46b3521ce464530c70ec8441458bb86f9d089458bb06448ce296f2a11b6.png","timeStamp":1722891888836,"screenshotName":"afddf46b3521ce464530c70ec8441458bb86f9d089458bb06448ce296f2a11b6.png"}],"result":"SUCCESS","precondition":false,"level":2},{"number":16,"description":"actor enters \u0027UdN_25\u0027 into By.id: Serenity_Pro_Organization_BusinessUnitDialog3_Name","duration":314,"startTime":"2024-08-05T16:04:48.836600200-05:00[America/Panama]","screenshots":[{"screenshot":"a77a5d0b9fa9a40eb99fa40c834e22826c6719901fa8322f7e8694a1cbf12208.png","timeStamp":1722891889151,"screenshotName":"a77a5d0b9fa9a40eb99fa40c834e22826c6719901fa8322f7e8694a1cbf12208.png"}],"result":"SUCCESS","precondition":false,"level":2},{"number":17,"description":"actor clicks on [By.id: select2-chosen-1]","duration":435,"startTime":"2024-08-05T16:04:49.151196-05:00[America/Panama]","screenshots":[{"screenshot":"526bbc913e48c523cb596b14a92a321a81f01a9985736a8d662992810f2c761f.png","timeStamp":1722891889586,"screenshotName":"526bbc913e48c523cb596b14a92a321a81f01a9985736a8d662992810f2c761f.png"}],"result":"SUCCESS","precondition":false,"level":2},{"number":18,"description":"actor enters \u0027Catherine\u0027 into By.id: s2id_autogen1_search","duration":423,"startTime":"2024-08-05T16:04:49.601419900-05:00[America/Panama]","screenshots":[{"screenshot":"80ed9e3658b470288bf7952b6c726e056ad88eea4d07fd2c256c93dc3db230d8.png","timeStamp":1722891890024,"screenshotName":"80ed9e3658b470288bf7952b6c726e056ad88eea4d07fd2c256c93dc3db230d8.png"}],"result":"SUCCESS","precondition":false,"level":2},{"number":19,"description":"actor hits the \u0027ARROW_DOWN\u0027 key#pluraliser","duration":265,"startTime":"2024-08-05T16:04:50.025522200-05:00[America/Panama]","screenshots":[{"screenshot":"3a0bfc63e525ba009dd02893990490e194865f1628fe04467adc53b6a4531fb2.png","timeStamp":1722891890291,"screenshotName":"3a0bfc63e525ba009dd02893990490e194865f1628fe04467adc53b6a4531fb2.png"}],"result":"SUCCESS","precondition":false,"level":2},{"number":20,"description":"actor hits the \u0027ENTER\u0027 key#pluraliser","duration":281,"startTime":"2024-08-05T16:04:50.291366800-05:00[America/Panama]","screenshots":[{"screenshot":"845aa9874a2c5e14acf399e589103c31cf318e100e7beebb82f2dd2fc97b2940.png","timeStamp":1722891890572,"screenshotName":"845aa9874a2c5e14acf399e589103c31cf318e100e7beebb82f2dd2fc97b2940.png"}],"result":"SUCCESS","precondition":false,"level":2},{"number":21,"description":"actor clicks on BOTON_GUARDAR","duration":668,"startTime":"2024-08-05T16:04:50.576765200-05:00[America/Panama]","screenshots":[{"screenshot":"c0e35456925482ecdac08eaca138965af214981bab42d6fd6aa5661fabde5688.png","timeStamp":1722891891243,"screenshotName":"c0e35456925482ecdac08eaca138965af214981bab42d6fd6aa5661fabde5688.png"}],"result":"SUCCESS","precondition":false,"level":2}]}]},{"number":22,"description":"Entonces El sistema creara una nueva unidad de negocio","duration":800,"startTime":"2024-08-05T16:04:51.519396200-05:00[America/Panama]","screenshots":[{"screenshot":"bec6a6c453bd08296f48f0bee60287eb62f56fa5b4aa0e0fd24c9bc33ac2ae43.png","timeStamp":1722891892319,"screenshotName":"bec6a6c453bd08296f48f0bee60287eb62f56fa5b4aa0e0fd24c9bc33ac2ae43.png"}],"result":"SUCCESS","precondition":false,"level":0,"children":[{"number":23,"description":"Then validar nueva unidad de negocios should be a string containing \u0027UdN_25\u0027","duration":416,"startTime":"2024-08-05T16:04:51.872227400-05:00[America/Panama]","screenshots":[{"screenshot":"bec6a6c453bd08296f48f0bee60287eb62f56fa5b4aa0e0fd24c9bc33ac2ae43.png","timeStamp":1722891892288,"screenshotName":"bec6a6c453bd08296f48f0bee60287eb62f56fa5b4aa0e0fd24c9bc33ac2ae43.png"}],"result":"SUCCESS","precondition":false,"level":1}]}],"userStory":{"id":"casos","storyName":"Agendar una reunión a unidad de negocio y asociar contacto previamente creados","displayName":"Agendar una reunión a unidad de negocio y asociar contacto previamente creados","path":"casos","pathElements":[{"name":"casos","description":""}],"type":"feature"},"title":"Crear una nueva unidad de negocio","description":"","backgroundTitle":"","backgroundDescription":"","tags":[{"name":"Chrome","type":"context","displayName":"Chrome"},{"name":"Windows","type":"context","displayName":"Windows"},{"name":"CasoUnidadDeNegocio","type":"tag","displayName":"CasoUnidadDeNegocio"},{"name":"Chrome, Windows","type":"context","displayName":"Chrome, Windows"},{"name":"HistoriaDeUsuario","type":"tag","displayName":"HistoriaDeUsuario"}],"startTime":"2024-08-05T16:04:22.046562100-05:00[America/Panama]","duration":11585,"projectKey":"","sessionId":"bf09f46c601b1cc0a46ba584bc416bed","driver":"chrome:actor","isManualTestingUpToDate":false,"context":"chrome,windows","manual":false,"testSource":"Cucumber","actors":[{"name":"actor","can":["browse the web"]}],"order":0,"result":"SUCCESS"}